Metadata-Version: 2.1
Name: image-preprocessorpy
Version: 1.0.1
Summary: A package for preprocessing images by resizing and cropping them to a target size.
Home-page: https://github.com/avinrique/image-preprocessor
Author: Avinrique
Author-email: avigupta2001ad@gmail.com
Classifier: Programming Language :: Python :: 3
Classifier: License :: OSI Approved :: MIT License
Classifier: Operating System :: OS Independent
Requires-Dist: Pillow>=8.4.0
